Workbook

Sheet Backlog
A1: NutriPlan AI — Product Backlog (Scrum)
A2: Ordenado por prioridad. Sprints sugeridos de 2 semanas, equipo de 5-6 personas. Story points en escala Fibonacci.
A4: ID | B4: Épica | C4: Descripción de la épica | D4: Subárea | E4: Historia de usuario | F4: Prioridad | G4: MoSCoW | H4: Story Points | I4: Sprint sugerido | J4: Criterios de aceptación | K4: Estado
A5: HU-01 | B5: Compras, presupuesto y despensa | C5: Convierte el plan de comidas en una lista de compras accionable, controla el gasto frente al presupuesto declarado, reduce el desperdicio de alimentos y prepara el terreno para foto/OCR e integraciones con supermercados. | D5: Compras | E5: Como usuario, quiero generar automáticamente la lista de compras a partir de mi plan semanal, para no armarla manualmente. | F5: Alta | G5: Must | H5: 8 | I5: Sprint 3 | J5: Dado un plan semanal ya generado con 21 comidas, cuando toco "Generar lista de compras", entonces los ingredientes que se repiten en 2 o más recetas aparecen como una sola línea con la suma exacta de cantidades (ej. "3 tazas de garbanzos" en vez de 3 líneas separadas). | K5: Por hacer
A6: HU-02 | B6: Compras, presupuesto y despensa | C6: Convierte el plan de comidas en una lista de compras accionable, controla el gasto frente al presupuesto declarado, reduce el desperdicio de alimentos y prepara el terreno para foto/OCR e integraciones con supermercados. | D6: Compras | E6: Como usuario, quiero que los ingredientes que ya tengo en despensa no aparezcan como pendientes de comprar. | F6: Alta | G6: Must | H6: 5 | I6: Sprint 3 | J6: Dado que tengo 200g de lentejas en despensa y el plan requiere 250g en total, cuando se genera la lista de compras, entonces el ítem "lentejas" aparece con cantidad neta a comprar = 50g. Caso borde: si la despensa cubre el 100% del requerimiento, el ítem aparece tachado con la nota "ya tienes esto" en vez de omitirse silenciosamente. | K6: Por hacer
A7: HU-03 | B7: Compras, presupuesto y despensa | C7: Convierte el plan de comidas en una lista de compras accionable, controla el gasto frente al presupuesto declarado, reduce el desperdicio de alimentos y prepara el terreno para foto/OCR e integraciones con supermercados. | D7: Compras | E7: Como usuario, quiero tachar o eliminar ítems de la lista manualmente, para ajustarla a mi realidad. | F7: Alta | G7: Must | H7: 2 | I7: Sprint 3 | J7: Dado que estoy viendo mi lista de compras, cuando toco el checkbox de un ítem, entonces el ítem se tacha visualmente y se mueve al final de su sección; además puedo agregar un ítem libre mediante un campo de texto que no queda vinculado a ninguna receta. | K7: Por hacer
A8: HU-04 | B8: Compras, presupuesto y despensa | C8: Convierte el plan de comidas en una lista de compras accionable, controla el gasto frente al presupuesto declarado, reduce el desperdicio de alimentos y prepara el terreno para foto/OCR e integraciones con supermercados. | D8: Presupuesto | E8: Como usuario, quiero ver el costo estimado de mi plan semanal antes de ir a comprar, para saber si se ajusta a mi presupuesto. | F8: Alta | G8: Must | H8: 8 | I8: Sprint 3 | J8: Dado un plan semanal generado, cuando abro el resumen, entonces veo el costo total estimado (suma de precio_promedio x cantidad por ingrediente) desglosado por receta, con la fuente y antigüedad del precio visible (ej. "precios promedio Nariño, actualizados hace 5 días"). | K8: Por hacer
A9: HU-05 | B9: Compras, presupuesto y despensa | C9: Convierte el plan de comidas en una lista de compras accionable, controla el gasto frente al presupuesto declarado, reduce el desperdicio de alimentos y prepara el terreno para foto/OCR e integraciones con supermercados. | D9: Presupuesto | E9: Como usuario, quiero que la app me avise si mi plan supera el presupuesto declarado, antes de confirmarlo. | F9: Alta | G9: Must | H9: 5 | I9: Sprint 4 | J9: Dado un presupuesto semanal de $60.000 y un plan con costo estimado de $68.000, cuando intento confirmar el plan, entonces aparece una alerta bloqueante "Tu plan cuesta $8.000 más de tu presupuesto" con las opciones "Ajustar automáticamente" y "Confirmar de todos modos"; no puedo avanzar sin elegir una. | K9: Por hacer
A10: HU-06 | B10: Comunidad y confianza | C10: Habilita el intercambio social de recetas y comentarios entre usuarios, y protege los datos sensibles con cifrado, consentimiento y moderación de contenido. | D10: Privacidad | E10: Como usuario, quiero que mis datos de salud (alergias, peso, condiciones médicas) estén cifrados, para proteger mi información sensible. | F10: Alta | G10: Must | H10: 8 | I10: Sprint 1 | J10: Dado que guardo una condición médica en mi perfil, cuando el dato se transmite del cliente al servidor y se almacena, entonces la transmisión usa TLS 1.2 o superior y el campo se almacena cifrado en la base de datos, verificable en una auditoría de seguridad; ningún log de la aplicación muestra el valor en texto plano. | K10: Por hacer
A11: HU-07 | B11: Comunidad y confianza | C11: Habilita el intercambio social de recetas y comentarios entre usuarios, y protege los datos sensibles con cifrado, consentimiento y moderación de contenido. | D11: Privacidad | E11: Como usuario, quiero poder exportar o eliminar todos mis datos de la app, para tener control sobre mi información. | F11: Alta | G11: Must | H11: 5 | I11: Sprint 4 | J11: Dado que estoy en configuración de privacidad, cuando toco "Eliminar mi cuenta y datos" y confirmo reingresando mi contraseña, entonces todos mis datos personales se eliminan o anonimizan en un plazo máximo de 30 días, con confirmación enviada por correo. | K11: Por hacer
A12: HU-08 | B12: Nutrición y feedback | C12: Muestra información nutricional confiable por receta y por día, y usa las calificaciones y comentarios del usuario para mejorar las próximas recomendaciones. | D12: Nutrición | E12: Como usuario, quiero ver las calorías y macronutrientes de cada receta por porción, para tomar decisiones informadas. | F12: Alta | G12: Must | H12: 5 | I12: Sprint 2 | J12: Dado cualquier receta del catálogo, cuando abro su detalle, entonces veo kcal, proteína (g), carbohidratos (g) y grasa (g) por porción, visibles sin necesidad de scroll adicional, calculados desde la base de datos nutricional (no estimados manualmente por el equipo de contenido). | K12: Por hacer
A13: HU-09 | B13: Nutrición y feedback | C13: Muestra información nutricional confiable por receta y por día, y usa las calificaciones y comentarios del usuario para mejorar las próximas recomendaciones. | D13: Feedback | E13: Como usuario, quiero calificar una receta después de cocinarla, para mejorar mis futuras recomendaciones. | F13: Alta | G13: Must | H13: 3 | I13: Sprint 3 | J13: Dado que marco una receta como "cocinada", cuando confirmo esa acción, entonces se despliega un selector de 1 a 5 estrellas obligatorio antes de cerrar el modal, y la calificación queda asociada a receta+usuario+fecha en el historial. | K13: Por hacer
A14: HU-10 | B14: Nutrición y feedback | C14: Muestra información nutricional confiable por receta y por día, y usa las calificaciones y comentarios del usuario para mejorar las próximas recomendaciones. | D14: Feedback | E14: Como usuario, quiero que mis calificaciones afecten las próximas recomendaciones, para no volver a ver recetas que no me gustaron. | F14: Alta | G14: Must | H14: 8 | I14: Sprint 4 | J14: Dado que califiqué "Sopa de lentejas" con 1 estrella, cuando se genera mi próximo plan semanal, entonces esa receta específica no vuelve a aparecer durante al menos 60 días, y recetas con ingredientes principales similares bajan su prioridad en el ranking un 20%. | K14: Por hacer
A15: HU-11 | B15: Perfil y personalización | C15: Captura y mantiene las preferencias, restricciones y ajustes finos del usuario (dieta, alergias, presupuesto, macros, tiempo de cocina) que alimentan cada recomendación de la app. | D15: Perfil | E15: Como usuaria nueva, quiero indicar mi tipo de dieta (omnívoro, vegetariano, vegano, etc.) para que la app filtre recetas compatibles desde el primer uso. | F15: Alta | G15: Must | H15: 3 | I15: Sprint 1 | J15: Dado que estoy en el paso "Estilo de alimentación", cuando selecciono "Vegetariano" y confirmo, entonces mi perfil guarda dieta_tipo="vegetariano" y el primer plan generado tiene 0% de recetas con carne o pescado como ingrediente principal. Caso borde: si no selecciono ninguna opción, el botón "Continuar" queda deshabilitado y se muestra "Selecciona una opción para continuar". | K15: Por hacer
A16: HU-12 | B16: Perfil y personalización | C16: Captura y mantiene las preferencias, restricciones y ajustes finos del usuario (dieta, alergias, presupuesto, macros, tiempo de cocina) que alimentan cada recomendación de la app. | D16: Perfil | E16: Como usuaria con alergias, quiero declarar mis alergias alimentarias para que la app nunca me sugiera recetas que las contengan. | F16: Alta | G16: Must | H16: 5 | I16: Sprint 1 | J16: Dado que marqué "Frutos secos" y "Mariscos" como alergias, cuando se genera cualquier plan o resultado de búsqueda, entonces 0 recetas devueltas contienen esos alérgenos en su lista de ingredientes, incluida cualquier sustitución sugerida. Caso borde: si una receta ya guardada en mis favoritos contiene un alérgeno recién declarado, se elimina automáticamente de favoritos y se me notifica el motivo. | K16: Por hacer
... A58: HU-54 | B58: Planificación inteligente de comidas | C58: Genera, ajusta y explica los planes de comidas diarios y semanales: motor de recomendación, escalado de porciones, adaptación de recetas, asistente conversacional y recordatorios. | D58: Asistente IA | E58: Como usuario, quiero usar respuestas rápidas predefinidas en el chat, para no tener que escribir siempre mi pedido. | F58: Baja | G58: Could | H58: 3 | I58: Backlog futuro | J58: Dado que abro el asistente por primera vez en el día, cuando se carga la pantalla, entonces se muestran exactamente 3 chips de pedidos frecuentes basados en mi historial de uso (ej. si suelo pedir "menos calorías", ese chip aparece primero). | K58: Por hacer

Sheet Resumen
A1: Resumen del backlog
A3: Por prioridad
A4: Prioridad | B4: Historias | C4: Story points
A5: Alta | B5: =COUNTIF(Backlog!F:F,A5) -> 18 | C5: =SUMIF(Backlog!F:F,A5,Backlog!H:H) -> 99
A6: Media | B6: =COUNTIF(Backlog!F:F,A6) -> 23 | C6: =SUMIF(Backlog!F:F,A6,Backlog!H:H) -> 105
A7: Baja | B7: =COUNTIF(Backlog!F:F,A7) -> 13 | C7: =SUMIF(Backlog!F:F,A7,Backlog!H:H) -> 101
A8: Total | B8: =SUM(B5:B7) -> 54 | C8: =SUM(C5:C7) -> 305
A11: Por épica
A12: Épica | B12: Historias | C12: Story points
A13: Compras, presupuesto y despensa | B13: =COUNTIF(Backlog!B:B,A13) -> 16 | C13: =SUMIF(Backlog!B:B,A13,Backlog!H:H) -> 117
A14: Comunidad y confianza | B14: =COUNTIF(Backlog!B:B,A14) -> 6 | C14: =SUMIF(Backlog!B:B,A14,Backlog!H:H) -> 37
A15: Nutrición y feedback | B15: =COUNTIF(Backlog!B:B,A15) -> 6 | C15: =SUMIF(Backlog!B:B,A15,Backlog!H:H) -> 32
A16: Perfil y personalización | B16: =COUNTIF(Backlog!B:B,A16) -> 12 | C16: =SUMIF(Backlog!B:B,A16,Backlog!H:H) -> 41
A17: Planificación inteligente de comidas | B17: =COUNTIF(Backlog!B:B,A17) -> 14 | C17: =SUMIF(Backlog!B:B,A17,Backlog!H:H) -> 78
A20: Por sprint
A21: Sprint | B21: Historias | C21: Story points
A22: Sprint 1 | B22: =COUNTIF(Backlog!I:I,A22) -> 5 | C22: =SUMIF(Backlog!I:I,A22,Backlog!H:H) -> 21
A23: Sprint 2 | B23: =COUNTIF(Backlog!I:I,A23) -> 5 | C23: =SUMIF(Backlog!I:I,A23,Backlog!H:H) -> 34
A24: Sprint 3 | B24: =COUNTIF(Backlog!I:I,A24) -> 7 | C24: =SUMIF(Backlog!I:I,A24,Backlog!H:H) -> 31
A25: Sprint 4 | B25: =COUNTIF(Backlog!I:I,A25) -> 7 | C25: =SUMIF(Backlog!I:I,A25,Backlog!H:H) -> 32
A26: Sprint 5 | B26: =COUNTIF(Backlog!I:I,A26) -> 9 | C26: =SUMIF(Backlog!I:I,A26,Backlog!H:H) -> 39
A27: Sprint 6 | B27: =COUNTIF(Backlog!I:I,A27) -> 6 | C27: =SUMIF(Backlog!I:I,A27,Backlog!H:H) -> 34
A28: Sprint 7 | B28: =COUNTIF(Backlog!I:I,A28) -> 2 | C28: =SUMIF(Backlog!I:I,A28,Backlog!H:H) -> 13
A29: Backlog futuro | B29: =COUNTIF(Backlog!I:I,A29) -> 13 | C29: =SUMIF(Backlog!I:I,A29,Backlog!H:H) -> 101
